fmristats/__init__.py
fmristats/affines.py
fmristats/ants.py
fmristats/ati.py
fmristats/diffeomorphisms.py
fmristats/epilog.py
fmristats/euler.py
fmristats/filters.py
fmristats/fit.py
fmristats/fitdepreciated.py
fmristats/fsl.py
fmristats/grubbs.py
fmristats/irritation.py
fmristats/load.py
fmristats/lock.py
fmristats/matlab.py
fmristats/meta.py
fmristats/name.py
fmristats/nifti.py
fmristats/observations.py
fmristats/plot.py
fmristats/pmap.py
fmristats/pmodel.py
fmristats/protocol.py
fmristats/reference.py
fmristats/sample.py
fmristats/session.py
fmristats/smodel.py
fmristats/stimulus.py
fmristats/study.py
fmristats/tau.py
fmristats/tracking.py
fmristats/cli/__init__.py
fmristats/cli/ants4pop.py
fmristats/cli/csv2dataframe.py
fmristats/cli/csv2design.py
fmristats/cli/fmriati.py
fmristats/cli/fmriblock.py
fmristats/cli/fmrifit.py
fmristats/cli/fmriinfo.py
fmristats/cli/fmrimap.py
fmristats/cli/fmripop.py
fmristats/cli/fmriprune.py
fmristats/cli/fmririgids.py
fmristats/cli/fmrisample.py
fmristats/cli/fmristudy.py
fmristats/cli/fsl2design.py
fmristats/cli/fsl2rigids.py
fmristats/cli/fsl4pop.py
fmristats/cli/fsl4prune.py
fmristats/cli/mat2block.py
fmristats/cli/nii2image.py
fmristats/cli/nii2session.py
fmristats/cli/ref2plot.py
fmristats/cli/spm2design.py
fmristats/cli/spm2rigids.py
fmristats/cmd/__init__.py
fmristats/cmd/df.py
fmristats/cmd/hp.py
fmristats/cmd/api/__init__.py
fmristats/cmd/api/fmriassessment.py
fmristats/cmd/api/fmriati.py
fmristats/cmd/api/fmridf.py
fmristats/cmd/api/fmrifit.py
fmristats/cmd/api/fmriirritation.py
fmristats/cmd/api/fmripop.py
fmristats/cmd/api/fmriprune.py
fmristats/cmd/api/fmririgid.py
fmristats/cmd/api/fmrisample.py
fmristats/cmd/exp/__init__.py
fmristats/cmd/exp/fit2nii.py
fmristats/cmd/exp/ses2nii.py
fmristats/cmd/imp/__init__.py
fmristats/cmd/imp/csv2covariate.py
fmristats/cmd/imp/csv2protocol.py
fmristats/cmd/imp/mat2irr.py
fmristats/cmd/imp/nii2img.py
fmristats-0.1.1.dist-info/METADATA
fmristats-0.1.1.dist-info/RECORD
fmristats-0.1.1.dist-info/WHEEL
fmristats-0.1.1.dist-info/entry_points.txt
fmristats-0.1.1.dist-info/top_level.txt
