Metadata-Version: 2.1
Name: fmristats
Version: 0.1.1
Summary: Modelling the data and not the images in FMRI
Home-page: https://fmristats.github.io/
Author: Thomas W. D. Möbius
Author-email: moebius@medinfo.uni-kiel.de
License: GPLv3+
Keywords: fmri neuroimaging neuroscience statistics
Platform: UNKNOWN
Classifier: Development Status :: 3 - Alpha
Classifier: Intended Audience :: Science/Research
Classifier: Topic :: Software Development :: Build Tools
Classifier: License :: OSI Approved :: GNU General Public License v3 or later (GPLv3+)
Classifier: Programming Language :: Python :: 3.7
Requires-Dist: numpy
Requires-Dist: scipy
Requires-Dist: scikit-image
Requires-Dist: pandas
Requires-Dist: statsmodels
Requires-Dist: matplotlib
Requires-Dist: nibabel
Requires-Dist: nipype
